md_ssg/__init__.py
md_ssg/__main__.py
md_ssg/cli.py
md_ssg-0.1.dist-info/licenses/LICENSE
md_ssg-0.1.dist-info/METADATA
md_ssg-0.1.dist-info/WHEEL
md_ssg-0.1.dist-info/entry_points.txt
md_ssg-0.1.dist-info/top_level.txt
md_ssg-0.1.dist-info/RECORD
