Metadata-Version: 2.4
Name: md-ssg
Version: 0.1
Summary: Create a static website from markdown files
Author: R.Keelan
License: Apache-2.0
Project-URL: Homepage, https://github.com/RKeelan/md-ssg
Project-URL: Changelog, https://github.com/RKeelan/md-ssg/releases
Project-URL: Issues, https://github.com/RKeelan/md-ssg/issues
Project-URL: CI, https://github.com/RKeelan/md-ssg/actions
Classifier: License :: OSI Approved :: Apache Software License
Requires-Python: >=3.8
License-File: LICENSE
Requires-Dist: click
Requires-Dist: jinja2
Requires-Dist: markdown
Requires-Dist: toml
Provides-Extra: test
Requires-Dist: coverage[toml]>=7.5; extra == "test"
Requires-Dist: pytest>=8.0; extra == "test"
Requires-Dist: pytest-cov>=5.0; extra == "test"
Dynamic: license-file
